my_prime_library/__init__.py
my_prime_library/sieve.py
tests/__init__.py
tests/test_sieve.py
my_prime_library-0.21.dist-info/METADATA
my_prime_library-0.21.dist-info/WHEEL
my_prime_library-0.21.dist-info/entry_points.txt
my_prime_library-0.21.dist-info/top_level.txt
my_prime_library-0.21.dist-info/RECORD
