Metadata-Version: 2.1
Name: my_prime_library
Version: 0.21
Summary: A Python library implementing the Sieve of Eratosthenes algorithm for prime number generation.
